mysensors/VERSION
mysensors/__init__.py
mysensors/const.py
mysensors/const_14.py
mysensors/const_15.py
mysensors/const_20.py
mysensors/const_21.py
mysensors/const_22.py
mysensors/gateway_mqtt.py
mysensors/gateway_serial.py
mysensors/gateway_tcp.py
mysensors/handler.py
mysensors/message.py
mysensors/mysensors.py
mysensors/ota.py
mysensors/persistence.py
mysensors/sensor.py
mysensors/task.py
mysensors/transport.py
mysensors/util.py
mysensors/validation.py
mysensors/cli/__init__.py
mysensors/cli/gateway_mqtt.py
mysensors/cli/gateway_serial.py
mysensors/cli/gateway_tcp.py
mysensors/cli/helper.py
pymysensors-0.25.2.dist-info/licenses/LICENSE
pymysensors-0.25.2.dist-info/METADATA
pymysensors-0.25.2.dist-info/WHEEL
pymysensors-0.25.2.dist-info/entry_points.txt
pymysensors-0.25.2.dist-info/top_level.txt
pymysensors-0.25.2.dist-info/RECORD
