Metadata-Version: 2.4
Name: pymysensors
Version: 0.25.2
Summary: Python API for talking to a MySensors gateway
Author-email: Theodor Lindquist <theodor.lindquist@gmail.com>
License-Expression: MIT
Project-URL: Source code, https://github.com/theolind/pymysensors
Keywords: sensor,actuator,IoT,DYI
Classifier: Intended Audience :: Developers
Classifier: Intended Audience :: End Users/Desktop
Classifier: Natural Language :: English
Classifier: Operating System :: OS Independent
Classifier: Programming Language :: Python :: 3.9
Classifier: Programming Language :: Python :: 3.10
Classifier: Programming Language :: Python :: 3.11
Classifier: Programming Language :: Python :: 3.12
Classifier: Programming Language :: Python :: 3.13
Classifier: Topic :: Home Automation
Requires-Python: >=3.9
License-File: LICENSE
Requires-Dist: awesomeversion
Requires-Dist: click
Requires-Dist: crcmod>=1.7
Requires-Dist: getmac
Requires-Dist: IntelHex>=2.2.1
Requires-Dist: pyserial>=3.4
Requires-Dist: pyserial-asyncio-fast>=0.16
Requires-Dist: voluptuous>=0.11.1
Provides-Extra: mqtt-client
Requires-Dist: paho-mqtt; extra == "mqtt-client"
Dynamic: license-file
